pyrangelist/__init__.py
pyrangelist/log.py
pyrangelist/range.py
pyrangelist/rangelist.py
pyrangelist/rangelist_naive.py
pyrangelist-0.1.2.dist-info/LICENSE
pyrangelist-0.1.2.dist-info/METADATA
pyrangelist-0.1.2.dist-info/WHEEL
pyrangelist-0.1.2.dist-info/top_level.txt
pyrangelist-0.1.2.dist-info/RECORD
