Metadata-Version: 2.1
Name: pyrangelist
Version: 0.1.2
Summary: Implementation of the RangeList datastructure in python. 
Home-page: UNKNOWN
Author: Sergiy Popovych
Author-email: sergiy.popovich@gmail.com
License: UNKNOWN
Platform: UNKNOWN
Requires-Python: >=3.8
License-File: LICENSE
Requires-Dist: intervaltree
Provides-Extra: dev
Requires-Dist: pytest ; extra == 'dev'
Requires-Dist: pytest-cov ; extra == 'dev'
Requires-Dist: astroid ; extra == 'dev'
Requires-Dist: isort ; extra == 'dev'
Requires-Dist: pylint ; extra == 'dev'
Requires-Dist: black ; extra == 'dev'
Requires-Dist: twine ; extra == 'dev'
